[
    {
        "id": "5E4922B039CC",
        "landId": "270536532EED",
        "project": "绿地未来商业中心",
        "use": "商业服务业设施用地、兼容办公、文化娱乐用地",
        "developer": "佛山铂晟置业有限公司",
        "content": "bbbb",
        "datetime": "2016-05-14 12:02:11"
    },
    {
        "id": "68B6CBA7E927",
        "landId": "FCECF02ADEFC",
        "project": "AA00111",
        "use": "bbbbbbbbbb",
        "developer": "开发商开发商开发商开发商",
        "content": "ddddddddddddddd",
        "datetime": "2016-05-14 15:03:45"
    },
    {
        "id": "B3B15DDD5A7E",
        "landId": "F1E1DFCF17D3",
        "project": "sgadfsd",
        "use": "22",
        "developer": "eew",
        "content": "sdfsdf",
        "datetime": "2016-05-14 15:12:47"
    },
    {
        "id": "8446CDFB99D6",
        "landId": "82F8DDE3D224",
        "project": "sdfa",
        "use": "asdf",
        "developer": "sdf",
        "content": "asdf",
        "datetime": "2016-05-14 15:15:07"
    },
    {
        "id": "4C8897EC99F6",
        "landId": "1B776B28C7CF",
        "project": "a",
        "use": "b",
        "developer": "c",
        "content": "d",
        "datetime": "2016-05-14 19:47:38"
    },
    {
        "id": "410AFBDF1CB3",
        "landId": "BE6D1EFCB85A",
        "project": "aa",
        "use": "bdfsa",
        "developer": "c",
        "content": "d",
        "datetime": "2016-05-16 11:47:40"
    },
    {
        "id": "9318C9B7431F",
        "landId": "768131EC733A",
        "project": "ttttt-000",
        "use": "atttt-222",
        "developer": "btttt",
        "content": "ctttt",
        "datetime": "2016-05-16 16:06:40"
    }
]