{
    "list": [
        {
            "license": {
                "id": "9042B8F13BEF",
                "datetime": "2016-06-15 19:27:45",
                "planId": "3D2EFAC16E99",
                "number": "建字第440604201600119号",
                "numberDesc": "",
                "name": "",
                "nameDesc": "",
                "date": "2016-05-06",
                "dateDesc": "",
                "residenceSize": 43042.41,
                "residenceSizeDesc": "",
                "commerceSize": 1391.48,
                "commerceSizeDesc": "",
                "officeSize": 0,
                "officeSizeDesc": "",
                "otherSize": 92.43,
                "otherSizeDesc": "",
                "parkSize": 15600.47,
                "parkSizeDesc": "",
                "otherSize1": 2917.39,
                "otherSize1Desc": ""
            },
            "plan": {
                "id": "3D2EFAC16E99",
                "datetime": "2016-06-15 19:05:08",
                "landId": "CDF0F933963D",
                "project": "保利碧桂园天汇花园地块一保利碧桂园天旭花园、天盈花园",
                "projectDesc": "",
                "use": "地块一：商业商务娱乐康体用地，兼容二类居住用地；地块二、三：二类居住用地，兼容商业、商务用地",
                "useDesc": "",
                "developer": "佛山保利源泰房地产有限公司",
                "developerDesc": ""
            },
            "land": {
                "id": "CDF0F933963D",
                "datetime": "2016-06-24 17:45:57",
                "number": "TD2015(CC)WG009",
                "numberDesc": "",
                "town": "石湾",
                "townDesc": "",
                "location": "魁奇路南侧、桂澜路东侧",
                "locationDesc": "",
                "size": 136354.27,
                "sizeDesc": "",
                "use": "二类居住用地，商业商务娱乐康体用地",
                "useDesc": "",
                "diy": false,
                "diyDesc": "",
                "residenceSize": 191261,
                "residenceSizeDesc": "",
                "commerceSize": 210564,
                "commerceSizeDesc": "",
                "officeSize": 0,
                "officeSizeDesc": "",
                "otherSize": 0,
                "otherSizeDesc": "",
                "parkSize": 119995,
                "parkSizeDesc": "",
                "otherSize1": 0,
                "otherSize1Desc": "",
                "winner": "保利华南实业有限公司",
                "winnerDesc": "",
                "price": 195877,
                "priceDesc": "",
                "date": "2015-10-30",
                "dateDesc": "",
                "contract": "440601-2015-100058",
                "contractDesc": "",
                "license": "",
                "licenseDesc": "未发证"
            }
        },
        {
            "license": {
                "id": "1D48875A059C",
                "datetime": "2016-06-15 19:27:30",
                "planId": "3D2EFAC16E99",
                "number": "建字第440604201600117号",
                "numberDesc": "",
                "name": "",
                "nameDesc": "",
                "date": "2016-05-06",
                "dateDesc": "",
                "residenceSize": 56611.09,
                "residenceSizeDesc": "",
                "commerceSize": 1290.35,
                "commerceSizeDesc": "",
                "officeSize": 0,
                "officeSizeDesc": "",
                "otherSize": 542.35,
                "otherSizeDesc": "",
                "parkSize": 9820.84,
                "parkSizeDesc": "",
                "otherSize1": 2960.58,
                "otherSize1Desc": ""
            },
            "plan": {
                "id": "3D2EFAC16E99",
                "datetime": "2016-06-15 19:05:08",
                "landId": "CDF0F933963D",
                "project": "保利碧桂园天汇花园地块一保利碧桂园天旭花园、天盈花园",
                "projectDesc": "",
                "use": "地块一：商业商务娱乐康体用地，兼容二类居住用地；地块二、三：二类居住用地，兼容商业、商务用地",
                "useDesc": "",
                "developer": "佛山保利源泰房地产有限公司",
                "developerDesc": ""
            },
            "land": {
                "id": "CDF0F933963D",
                "datetime": "2016-06-24 17:45:57",
                "number": "TD2015(CC)WG009",
                "numberDesc": "",
                "town": "石湾",
                "townDesc": "",
                "location": "魁奇路南侧、桂澜路东侧",
                "locationDesc": "",
                "size": 136354.27,
                "sizeDesc": "",
                "use": "二类居住用地，商业商务娱乐康体用地",
                "useDesc": "",
                "diy": false,
                "diyDesc": "",
                "residenceSize": 191261,
                "residenceSizeDesc": "",
                "commerceSize": 210564,
                "commerceSizeDesc": "",
                "officeSize": 0,
                "officeSizeDesc": "",
                "otherSize": 0,
                "otherSizeDesc": "",
                "parkSize": 119995,
                "parkSizeDesc": "",
                "otherSize1": 0,
                "otherSize1Desc": "",
                "winner": "保利华南实业有限公司",
                "winnerDesc": "",
                "price": 195877,
                "priceDesc": "",
                "date": "2015-10-30",
                "dateDesc": "",
                "contract": "440601-2015-100058",
                "contractDesc": "",
                "license": "",
                "licenseDesc": "未发证"
            }
        },
        {
            "license": {
                "id": "245B00FA9E82",
                "datetime": "2016-06-15 19:27:16",
                "planId": "3D2EFAC16E99",
                "number": "建字第440604201600132号",
                "numberDesc": "",
                "name": "",
                "nameDesc": "",
                "date": "2016-05-20",
                "dateDesc": "",
                "residenceSize": 0,
                "residenceSizeDesc": "",
                "commerceSize": 0,
                "commerceSizeDesc": "",
                "officeSize": 0,
                "officeSizeDesc": "",
                "otherSize": 5720.56,
                "otherSizeDesc": "幼儿园",
                "parkSize": 0,
                "parkSizeDesc": "",
                "otherSize1": 301.7,
                "otherSize1Desc": ""
            },
            "plan": {
                "id": "3D2EFAC16E99",
                "datetime": "2016-06-15 19:05:08",
                "landId": "CDF0F933963D",
                "project": "保利碧桂园天汇花园地块一保利碧桂园天旭花园、天盈花园",
                "projectDesc": "",
                "use": "地块一：商业商务娱乐康体用地，兼容二类居住用地；地块二、三：二类居住用地，兼容商业、商务用地",
                "useDesc": "",
                "developer": "佛山保利源泰房地产有限公司",
                "developerDesc": ""
            },
            "land": {
                "id": "CDF0F933963D",
                "datetime": "2016-06-24 17:45:57",
                "number": "TD2015(CC)WG009",
                "numberDesc": "",
                "town": "石湾",
                "townDesc": "",
                "location": "魁奇路南侧、桂澜路东侧",
                "locationDesc": "",
                "size": 136354.27,
                "sizeDesc": "",
                "use": "二类居住用地，商业商务娱乐康体用地",
                "useDesc": "",
                "diy": false,
                "diyDesc": "",
                "residenceSize": 191261,
                "residenceSizeDesc": "",
                "commerceSize": 210564,
                "commerceSizeDesc": "",
                "officeSize": 0,
                "officeSizeDesc": "",
                "otherSize": 0,
                "otherSizeDesc": "",
                "parkSize": 119995,
                "parkSizeDesc": "",
                "otherSize1": 0,
                "otherSize1Desc": "",
                "winner": "保利华南实业有限公司",
                "winnerDesc": "",
                "price": 195877,
                "priceDesc": "",
                "date": "2015-10-30",
                "dateDesc": "",
                "contract": "440601-2015-100058",
                "contractDesc": "",
                "license": "",
                "licenseDesc": "未发证"
            }
        },
        {
            "license": {
                "id": "A210F0BF2323",
                "datetime": "2016-06-15 19:27:04",
                "planId": "3D2EFAC16E99",
                "number": "建字第440604201600103号",
                "numberDesc": "",
                "name": "",
                "nameDesc": "",
                "date": "2016-04-26",
                "dateDesc": "",
                "residenceSize": 66790.17,
                "residenceSizeDesc": "",
                "commerceSize": 4571.38,
                "commerceSizeDesc": "",
                "officeSize": 0,
                "officeSizeDesc": "",
                "otherSize": 2501.2,
                "otherSizeDesc": "",
                "parkSize": 22564.81,
                "parkSizeDesc": "",
                "otherSize1": 2383.46,
                "otherSize1Desc": ""
            },
            "plan": {
                "id": "3D2EFAC16E99",
                "datetime": "2016-06-15 19:05:08",
                "landId": "CDF0F933963D",
                "project": "保利碧桂园天汇花园地块一保利碧桂园天旭花园、天盈花园",
                "projectDesc": "",
                "use": "地块一：商业商务娱乐康体用地，兼容二类居住用地；地块二、三：二类居住用地，兼容商业、商务用地",
                "useDesc": "",
                "developer": "佛山保利源泰房地产有限公司",
                "developerDesc": ""
            },
            "land": {
                "id": "CDF0F933963D",
                "datetime": "2016-06-24 17:45:57",
                "number": "TD2015(CC)WG009",
                "numberDesc": "",
                "town": "石湾",
                "townDesc": "",
                "location": "魁奇路南侧、桂澜路东侧",
                "locationDesc": "",
                "size": 136354.27,
                "sizeDesc": "",
                "use": "二类居住用地，商业商务娱乐康体用地",
                "useDesc": "",
                "diy": false,
                "diyDesc": "",
                "residenceSize": 191261,
                "residenceSizeDesc": "",
                "commerceSize": 210564,
                "commerceSizeDesc": "",
                "officeSize": 0,
                "officeSizeDesc": "",
                "otherSize": 0,
                "otherSizeDesc": "",
                "parkSize": 119995,
                "parkSizeDesc": "",
                "otherSize1": 0,
                "otherSize1Desc": "",
                "winner": "保利华南实业有限公司",
                "winnerDesc": "",
                "price": 195877,
                "priceDesc": "",
                "date": "2015-10-30",
                "dateDesc": "",
                "contract": "440601-2015-100058",
                "contractDesc": "",
                "license": "",
                "licenseDesc": "未发证"
            }
        },
        {
            "license": {
                "id": "22D05B8EE4CB",
                "datetime": "2016-06-16 09:06:15",
                "planId": "404FB1F30C0D",
                "number": "建字第440604201500278号",
                "numberDesc": "",
                "name": "",
                "nameDesc": "",
                "date": "2015-10-12",
                "dateDesc": "",
                "residenceSize": 0,
                "residenceSizeDesc": "",
                "commerceSize": 6409.59,
                "commerceSizeDesc": "",
                "officeSize": 0,
                "officeSizeDesc": "",
                "otherSize": 0,
                "otherSizeDesc": "",
                "parkSize": 0,
                "parkSizeDesc": "",
                "otherSize1": 171.79,
                "otherSize1Desc": ""
            },
            "plan": {
                "id": "404FB1F30C0D",
                "datetime": "2016-06-16 09:23:34",
                "landId": "1DE1FB4CFD9A",
                "project": "佛禅网(挂)2014-003宗地南堤湾国瑞城项目",
                "projectDesc": "",
                "use": "商业商务、娱乐康体、文化设施",
                "useDesc": "",
                "developer": "佛山市国瑞南方地产开发有限公司",
                "developerDesc": ""
            },
            "land": {
                "id": "1DE1FB4CFD9A",
                "datetime": "2016-06-15 17:05:33",
                "number": "佛禅网(挂)2014—003",
                "numberDesc": "",
                "town": "祖庙",
                "townDesc": "",
                "location": "南堤路南侧、松风路东侧、永安路西侧",
                "locationDesc": "",
                "size": 90231.09,
                "sizeDesc": "",
                "use": "商业商务、娱乐康体、文化设施用地，可兼容二类居住用地",
                "useDesc": "",
                "diy": false,
                "diyDesc": "",
                "residenceSize": 20000,
                "residenceSizeDesc": "",
                "commerceSize": 151313.37,
                "commerceSizeDesc": "",
                "officeSize": 0,
                "officeSizeDesc": "",
                "otherSize": 0,
                "otherSizeDesc": "",
                "parkSize": 63023,
                "parkSizeDesc": "",
                "otherSize1": 0,
                "otherSize1Desc": "",
                "winner": "佛山市国瑞南方地产开发有限公司",
                "winnerDesc": "",
                "price": 148315,
                "priceDesc": "",
                "date": "2014-6-16",
                "dateDesc": "",
                "contract": "440601-2014-100033",
                "contractDesc": "",
                "license": "佛禅国用(2015)第1018423号|佛禅国用(2015)第1208810号|佛禅国用(2015)第1208811号|佛禅国用(2015)第1208812号|佛禅国用(2015)第1208813号|佛禅国用(2015)第1208980号",
                "licenseDesc": ""
            }
        },
        {
            "license": {
                "id": "69147B708F4D",
                "datetime": "2016-06-16 09:08:18",
                "planId": "404FB1F30C0D",
                "number": "建字第440604201500312号",
                "numberDesc": "",
                "name": "",
                "nameDesc": "",
                "date": "2015-11-18",
                "dateDesc": "",
                "residenceSize": 0,
                "residenceSizeDesc": "",
                "commerceSize": 8462.38,
                "commerceSizeDesc": "",
                "officeSize": 0,
                "officeSizeDesc": "",
                "otherSize": 0,
                "otherSizeDesc": "",
                "parkSize": 0,
                "parkSizeDesc": "",
                "otherSize1": 283.69,
                "otherSize1Desc": ""
            },
            "plan": {
                "id": "404FB1F30C0D",
                "datetime": "2016-06-16 09:23:34",
                "landId": "1DE1FB4CFD9A",
                "project": "佛禅网(挂)2014-003宗地南堤湾国瑞城项目",
                "projectDesc": "",
                "use": "商业商务、娱乐康体、文化设施",
                "useDesc": "",
                "developer": "佛山市国瑞南方地产开发有限公司",
                "developerDesc": ""
            },
            "land": {
                "id": "1DE1FB4CFD9A",
                "datetime": "2016-06-15 17:05:33",
                "number": "佛禅网(挂)2014—003",
                "numberDesc": "",
                "town": "祖庙",
                "townDesc": "",
                "location": "南堤路南侧、松风路东侧、永安路西侧",
                "locationDesc": "",
                "size": 90231.09,
                "sizeDesc": "",
                "use": "商业商务、娱乐康体、文化设施用地，可兼容二类居住用地",
                "useDesc": "",
                "diy": false,
                "diyDesc": "",
                "residenceSize": 20000,
                "residenceSizeDesc": "",
                "commerceSize": 151313.37,
                "commerceSizeDesc": "",
                "officeSize": 0,
                "officeSizeDesc": "",
                "otherSize": 0,
                "otherSizeDesc": "",
                "parkSize": 63023,
                "parkSizeDesc": "",
                "otherSize1": 0,
                "otherSize1Desc": "",
                "winner": "佛山市国瑞南方地产开发有限公司",
                "winnerDesc": "",
                "price": 148315,
                "priceDesc": "",
                "date": "2014-6-16",
                "dateDesc": "",
                "contract": "440601-2014-100033",
                "contractDesc": "",
                "license": "佛禅国用(2015)第1018423号|佛禅国用(2015)第1208810号|佛禅国用(2015)第1208811号|佛禅国用(2015)第1208812号|佛禅国用(2015)第1208813号|佛禅国用(2015)第1208980号",
                "licenseDesc": ""
            }
        },
        {
            "license": {
                "id": "99AF44BB484A",
                "datetime": "2016-06-16 09:20:42",
                "planId": "404FB1F30C0D",
                "number": "建字第440604201600112号",
                "numberDesc": "",
                "name": "",
                "nameDesc": "",
                "date": "2016-04-27",
                "dateDesc": "",
                "residenceSize": 7778.99,
                "residenceSizeDesc": "",
                "commerceSize": 0,
                "commerceSizeDesc": "",
                "officeSize": 0,
                "officeSizeDesc": "",
                "otherSize": 0,
                "otherSizeDesc": "",
                "parkSize": 23518.92,
                "parkSizeDesc": "",
                "otherSize1": 586.71,
                "otherSize1Desc": ""
            },
            "plan": {
                "id": "404FB1F30C0D",
                "datetime": "2016-06-16 09:23:34",
                "landId": "1DE1FB4CFD9A",
                "project": "佛禅网(挂)2014-003宗地南堤湾国瑞城项目",
                "projectDesc": "",
                "use": "商业商务、娱乐康体、文化设施",
                "useDesc": "",
                "developer": "佛山市国瑞南方地产开发有限公司",
                "developerDesc": ""
            },
            "land": {
                "id": "1DE1FB4CFD9A",
                "datetime": "2016-06-15 17:05:33",
                "number": "佛禅网(挂)2014—003",
                "numberDesc": "",
                "town": "祖庙",
                "townDesc": "",
                "location": "南堤路南侧、松风路东侧、永安路西侧",
                "locationDesc": "",
                "size": 90231.09,
                "sizeDesc": "",
                "use": "商业商务、娱乐康体、文化设施用地，可兼容二类居住用地",
                "useDesc": "",
                "diy": false,
                "diyDesc": "",
                "residenceSize": 20000,
                "residenceSizeDesc": "",
                "commerceSize": 151313.37,
                "commerceSizeDesc": "",
                "officeSize": 0,
                "officeSizeDesc": "",
                "otherSize": 0,
                "otherSizeDesc": "",
                "parkSize": 63023,
                "parkSizeDesc": "",
                "otherSize1": 0,
                "otherSize1Desc": "",
                "winner": "佛山市国瑞南方地产开发有限公司",
                "winnerDesc": "",
                "price": 148315,
                "priceDesc": "",
                "date": "2014-6-16",
                "dateDesc": "",
                "contract": "440601-2014-100033",
                "contractDesc": "",
                "license": "佛禅国用(2015)第1018423号|佛禅国用(2015)第1208810号|佛禅国用(2015)第1208811号|佛禅国用(2015)第1208812号|佛禅国用(2015)第1208813号|佛禅国用(2015)第1208980号",
                "licenseDesc": ""
            }
        },
        {
            "license": {
                "id": "B86E77E3CD3C",
                "datetime": "2016-06-16 09:23:31",
                "planId": "404FB1F30C0D",
                "number": "建字第440604201600091号",
                "numberDesc": "",
                "name": "",
                "nameDesc": "",
                "date": "2016-04-18",
                "dateDesc": "",
                "residenceSize": 0,
                "residenceSizeDesc": "",
                "commerceSize": 10145.45,
                "commerceSizeDesc": "",
                "officeSize": 0,
                "officeSizeDesc": "",
                "otherSize": 0,
                "otherSizeDesc": "",
                "parkSize": 0,
                "parkSizeDesc": "",
                "otherSize1": 1538.49,
                "otherSize1Desc": ""
            },
            "plan": {
                "id": "404FB1F30C0D",
                "datetime": "2016-06-16 09:23:34",
                "landId": "1DE1FB4CFD9A",
                "project": "佛禅网(挂)2014-003宗地南堤湾国瑞城项目",
                "projectDesc": "",
                "use": "商业商务、娱乐康体、文化设施",
                "useDesc": "",
                "developer": "佛山市国瑞南方地产开发有限公司",
                "developerDesc": ""
            },
            "land": {
                "id": "1DE1FB4CFD9A",
                "datetime": "2016-06-15 17:05:33",
                "number": "佛禅网(挂)2014—003",
                "numberDesc": "",
                "town": "祖庙",
                "townDesc": "",
                "location": "南堤路南侧、松风路东侧、永安路西侧",
                "locationDesc": "",
                "size": 90231.09,
                "sizeDesc": "",
                "use": "商业商务、娱乐康体、文化设施用地，可兼容二类居住用地",
                "useDesc": "",
                "diy": false,
                "diyDesc": "",
                "residenceSize": 20000,
                "residenceSizeDesc": "",
                "commerceSize": 151313.37,
                "commerceSizeDesc": "",
                "officeSize": 0,
                "officeSizeDesc": "",
                "otherSize": 0,
                "otherSizeDesc": "",
                "parkSize": 63023,
                "parkSizeDesc": "",
                "otherSize1": 0,
                "otherSize1Desc": "",
                "winner": "佛山市国瑞南方地产开发有限公司",
                "winnerDesc": "",
                "price": 148315,
                "priceDesc": "",
                "date": "2014-6-16",
                "dateDesc": "",
                "contract": "440601-2014-100033",
                "contractDesc": "",
                "license": "佛禅国用(2015)第1018423号|佛禅国用(2015)第1208810号|佛禅国用(2015)第1208811号|佛禅国用(2015)第1208812号|佛禅国用(2015)第1208813号|佛禅国用(2015)第1208980号",
                "licenseDesc": ""
            }
        },
        {
            "license": {
                "id": "BE7C972FE303",
                "datetime": "2016-06-16 12:00:56",
                "planId": "D74E09ABBB57",
                "number": "建字第440604201100282号",
                "numberDesc": "",
                "name": "",
                "nameDesc": "",
                "date": "2011-12-30",
                "dateDesc": "",
                "residenceSize": 119543.22,
                "residenceSizeDesc": "",
                "commerceSize": 5416.67,
                "commerceSizeDesc": "",
                "officeSize": 46943.66,
                "officeSizeDesc": "",
                "otherSize": 605.56,
                "otherSizeDesc": "",
                "parkSize": 71276.3,
                "parkSizeDesc": "",
                "otherSize1": 1352,
                "otherSize1Desc": ""
            },
            "plan": {
                "id": "D74E09ABBB57",
                "datetime": "2016-06-16 09:52:05",
                "landId": "A9F1FDFA9EDB",
                "project": "智慧新城",
                "projectDesc": "",
                "use": "都市型产业用地，包括工业、商服、住宅",
                "useDesc": "",
                "developer": "佛山源海发展有限公司",
                "developerDesc": ""
            },
            "land": {
                "id": "A9F1FDFA9EDB",
                "datetime": "2016-07-05 11:11:24",
                "number": "佛禅(挂)2011—006",
                "numberDesc": "",
                "town": "张槎",
                "townDesc": "",
                "location": "禅城区季华二路南侧、佛开高速公路东侧",
                "locationDesc": "",
                "size": 279165.66,
                "sizeDesc": "",
                "use": "都市型产业用地，包括工业、商服、住宅",
                "useDesc": "",
                "diy": false,
                "diyDesc": "",
                "residenceSize": 90000,
                "residenceSizeDesc": "",
                "commerceSize": 472000,
                "commerceSizeDesc": "",
                "officeSize": 0,
                "officeSizeDesc": "",
                "otherSize": 388000,
                "otherSizeDesc": "",
                "parkSize": 270000,
                "parkSizeDesc": "",
                "otherSize1": 0,
                "otherSize1Desc": "",
                "winner": "佛山源海发展有限公司",
                "winnerDesc": "",
                "price": 83956,
                "priceDesc": "",
                "date": "2011-03-28",
                "dateDesc": "",
                "contract": "440601-2011-100019",
                "contractDesc": "",
                "license": "佛禅国用(2014)第1101099号|佛禅国用(2014)第1101991号|佛禅国用(2015)第1100399号|佛禅国用(2015)第1100234号|佛禅国用(2011)第1100591号|佛禅国用(2015)第1100233号|佛禅国用(2011)第1100591号",
                "licenseDesc": ""
            }
        },
        {
            "license": {
                "id": "FA597809D2E5",
                "datetime": "2016-06-16 15:53:40",
                "planId": "0696E4D4E64C",
                "number": "建字第440604201500324号",
                "numberDesc": "",
                "name": "",
                "nameDesc": "",
                "date": "2015-11-23",
                "dateDesc": "",
                "residenceSize": 0,
                "residenceSizeDesc": "",
                "commerceSize": 31904.17,
                "commerceSizeDesc": "",
                "officeSize": 46521.59,
                "officeSizeDesc": "",
                "otherSize": 0,
                "otherSizeDesc": "",
                "parkSize": 28577.38,
                "parkSizeDesc": "",
                "otherSize1": 3744.96,
                "otherSize1Desc": ""
            },
            "plan": {
                "id": "0696E4D4E64C",
                "datetime": "2016-06-16 15:53:44",
                "landId": "CFFBB6C395A5",
                "project": "佛禅(挂)2010-022号地块项目",
                "projectDesc": "",
                "use": "地块一：商业办公文化用地，不兼容居住用地；地块二：居住用地，兼容商业办公用地",
                "useDesc": "",
                "developer": "佛山市禅城区祖庙街道镇安股份经济联合社、佛山市粤裕房地产投资有限公司",
                "developerDesc": ""
            },
            "land": {
                "id": "CFFBB6C395A5",
                "datetime": "2016-06-17 16:31:20",
                "number": "佛禅(挂)2010—022",
                "numberDesc": "",
                "town": "祖庙",
                "townDesc": "",
                "location": "禅城区季华六路北侧、南海大道西侧",
                "locationDesc": "",
                "size": 36919.56,
                "sizeDesc": "",
                "use": "地块一：商业办公文化用地，不兼容居住；地块二：居住用地，可兼容商业办公",
                "useDesc": "",
                "diy": false,
                "diyDesc": "",
                "residenceSize": 54174,
                "residenceSizeDesc": "",
                "commerceSize": 66706.72,
                "commerceSizeDesc": "",
                "officeSize": 0,
                "officeSizeDesc": "",
                "otherSize": 0,
                "otherSizeDesc": "",
                "parkSize": 42841,
                "parkSizeDesc": "",
                "otherSize1": 0,
                "otherSize1Desc": "",
                "winner": "佛山市粤裕房地产投资有限公司",
                "winnerDesc": "",
                "price": 12545.25,
                "priceDesc": "",
                "date": "2010-12-28",
                "dateDesc": "",
                "contract": "440601-2011-100010",
                "contractDesc": "",
                "license": "佛禅国用(2011)第1204283号|佛禅国用(2014)第1201280号|佛禅国用(2014)第1201281号",
                "licenseDesc": ""
            }
        },
        {
            "license": {
                "id": "5172E2DC9148",
                "datetime": "2016-06-16 17:34:06",
                "planId": "52B1266A5225",
                "number": "建字第440604201300338号",
                "numberDesc": "",
                "name": "",
                "nameDesc": "",
                "date": "2013-09-13",
                "dateDesc": "",
                "residenceSize": 0,
                "residenceSizeDesc": "",
                "commerceSize": 0,
                "commerceSizeDesc": "",
                "officeSize": 0,
                "officeSizeDesc": "",
                "otherSize": 3161.27,
                "otherSizeDesc": "幼儿园",
                "parkSize": 0,
                "parkSizeDesc": "",
                "otherSize1": 41.6,
                "otherSize1Desc": ""
            },
            "plan": {
                "id": "52B1266A5225",
                "datetime": "2016-06-16 17:39:45",
                "landId": "CD3CDDC19410",
                "project": "龙光水悦湾园",
                "projectDesc": "",
                "use": "二类居住用地，可兼容商业、办公、文化用地",
                "useDesc": "",
                "developer": "佛山市龙光阳光海岸房地产有限公司",
                "developerDesc": ""
            },
            "land": {
                "id": "CD3CDDC19410",
                "datetime": "2016-07-05 12:10:29",
                "number": "佛禅(挂)2012—001",
                "numberDesc": "",
                "town": "南庄",
                "townDesc": "",
                "location": "禅城区南庄镇南庄大道南侧、禅港路西侧",
                "locationDesc": "",
                "size": 111615.32,
                "sizeDesc": "",
                "use": "二类居住用地，可兼容商业、办公、文化用地",
                "useDesc": "",
                "diy": false,
                "diyDesc": "",
                "residenceSize": 223230,
                "residenceSizeDesc": "",
                "commerceSize": 55808,
                "commerceSizeDesc": "",
                "officeSize": 0,
                "officeSizeDesc": "",
                "otherSize": 0,
                "otherSizeDesc": "",
                "parkSize": 111476,
                "parkSizeDesc": "",
                "otherSize1": 0,
                "otherSize1Desc": "",
                "winner": "佛山市龙光阳光海岸房地产有限公司",
                "winnerDesc": "",
                "price": 24859.04,
                "priceDesc": "",
                "date": "2012-2-13",
                "dateDesc": "",
                "contract": "440601-2012-100040",
                "contractDesc": "",
                "license": "佛禅国用(2012)第0000972号|佛禅国用(2015)第0000094号|佛禅国用(2015)第0001329号|佛禅国用(2015)第0000046号|佛禅国用(2015)第0001328号|佛禅国用(2015)第0001327号",
                "licenseDesc": ""
            }
        },
        {
            "license": {
                "id": "7E5E6DC802F4",
                "datetime": "2016-06-17 17:18:57",
                "planId": "B8A0341D3E99",
                "number": "建字第440604200800159号",
                "numberDesc": "",
                "name": "",
                "nameDesc": "",
                "date": "2008-06-18",
                "dateDesc": "",
                "residenceSize": 0,
                "residenceSizeDesc": "",
                "commerceSize": 1702.2,
                "commerceSizeDesc": "",
                "officeSize": 0,
                "officeSizeDesc": "",
                "otherSize": 0,
                "otherSizeDesc": "",
                "parkSize": 0,
                "parkSizeDesc": "",
                "otherSize1": 0,
                "otherSize1Desc": ""
            },
            "plan": {
                "id": "B8A0341D3E99",
                "datetime": "2016-06-17 17:25:49",
                "landId": "F3BB05474906",
                "project": "佛山国际商业中心",
                "projectDesc": "",
                "use": "办公、商业、酒店式公寓及其配套设施",
                "useDesc": "",
                "developer": "广州市盈基投资有限公司",
                "developerDesc": ""
            },
            "land": {
                "id": "F3BB05474906",
                "datetime": "2016-06-27 09:09:27",
                "number": "佛禅(挂)2008-005",
                "numberDesc": "",
                "town": "祖庙",
                "townDesc": "",
                "location": "汾江中路东侧、城门头路北侧",
                "locationDesc": "",
                "size": 6372.31,
                "sizeDesc": "",
                "use": "办公、商业、酒店式公寓及配套服务设施",
                "useDesc": "",
                "diy": false,
                "diyDesc": "",
                "residenceSize": 0,
                "residenceSizeDesc": "",
                "commerceSize": 21347.44,
                "commerceSizeDesc": "",
                "officeSize": 0,
                "officeSizeDesc": "",
                "otherSize": 0,
                "otherSizeDesc": "",
                "parkSize": 6918.36,
                "parkSizeDesc": "",
                "otherSize1": 0,
                "otherSize1Desc": "",
                "winner": "广州市盈基智业发展有限公司",
                "winnerDesc": "",
                "price": 3295,
                "priceDesc": "",
                "date": "2008-4-9",
                "dateDesc": "",
                "contract": "440601-2008-100375、440601-2008-100376",
                "contractDesc": "",
                "license": "",
                "licenseDesc": "查询不到"
            }
        },
        {
            "license": {
                "id": "AB4B878755A9",
                "datetime": "2016-06-17 19:36:59",
                "planId": "FC3EDE99C78D",
                "number": "建字第440604201600130号",
                "numberDesc": "",
                "name": "",
                "nameDesc": "",
                "date": "2016-05-16",
                "dateDesc": "",
                "residenceSize": 0,
                "residenceSizeDesc": "",
                "commerceSize": 446.52,
                "commerceSizeDesc": "",
                "officeSize": 0,
                "officeSizeDesc": "",
                "otherSize": 0,
                "otherSizeDesc": "",
                "parkSize": 773.57,
                "parkSizeDesc": "",
                "otherSize1": 0,
                "otherSize1Desc": ""
            },
            "plan": {
                "id": "FC3EDE99C78D",
                "datetime": "2016-06-18 16:21:57",
                "landId": "FFFBB3D58A0B",
                "project": "泷景花园",
                "projectDesc": "",
                "use": "居住用地，兼容商业办公、文化娱乐用地等",
                "useDesc": "",
                "developer": "佛山市新锋房地产开发有限公司",
                "developerDesc": ""
            },
            "land": {
                "id": "FFFBB3D58A0B",
                "datetime": "2016-06-17 15:28:43",
                "number": "佛禅(挂)2009-014",
                "numberDesc": "",
                "town": "石湾",
                "townDesc": "",
                "location": "佛山大道东侧、前进路南侧、东平河北侧、纵二路西侧",
                "locationDesc": "",
                "size": 155956.28,
                "sizeDesc": "",
                "use": "居住用地，兼容商业办公、文化娱乐",
                "useDesc": "",
                "diy": false,
                "diyDesc": "",
                "residenceSize": 366020,
                "residenceSizeDesc": "",
                "commerceSize": 93115,
                "commerceSizeDesc": "",
                "officeSize": 0,
                "officeSizeDesc": "",
                "otherSize": 0,
                "otherSizeDesc": "",
                "parkSize": 116460,
                "parkSizeDesc": "",
                "otherSize1": 0,
                "otherSize1Desc": "",
                "winner": "佛山市新锋房地产开发有限公司",
                "winnerDesc": "",
                "price": 128601.77,
                "priceDesc": "",
                "date": "2009-12-30",
                "dateDesc": "",
                "contract": "440601-2010-100180",
                "contractDesc": "",
                "license": "佛禅国用(2012)第1003072号|佛禅国用(2012)第1008625号|佛禅国用(2012)第1008624号",
                "licenseDesc": ""
            }
        },
        {
            "license": {
                "id": "3B746336BD37",
                "datetime": "2016-06-17 19:40:24",
                "planId": "FC3EDE99C78D",
                "number": "建字第440604201600101号",
                "numberDesc": "",
                "name": "",
                "nameDesc": "",
                "date": "2016-04-22",
                "dateDesc": "",
                "residenceSize": 14478.22,
                "residenceSizeDesc": "",
                "commerceSize": 0,
                "commerceSizeDesc": "",
                "officeSize": 0,
                "officeSizeDesc": "",
                "otherSize": 0,
                "otherSizeDesc": "",
                "parkSize": 9893.07,
                "parkSizeDesc": "",
                "otherSize1": 8045.29,
                "otherSize1Desc": ""
            },
            "plan": {
                "id": "FC3EDE99C78D",
                "datetime": "2016-06-18 16:21:57",
                "landId": "FFFBB3D58A0B",
                "project": "泷景花园",
                "projectDesc": "",
                "use": "居住用地，兼容商业办公、文化娱乐用地等",
                "useDesc": "",
                "developer": "佛山市新锋房地产开发有限公司",
                "developerDesc": ""
            },
            "land": {
                "id": "FFFBB3D58A0B",
                "datetime": "2016-06-17 15:28:43",
                "number": "佛禅(挂)2009-014",
                "numberDesc": "",
                "town": "石湾",
                "townDesc": "",
                "location": "佛山大道东侧、前进路南侧、东平河北侧、纵二路西侧",
                "locationDesc": "",
                "size": 155956.28,
                "sizeDesc": "",
                "use": "居住用地，兼容商业办公、文化娱乐",
                "useDesc": "",
                "diy": false,
                "diyDesc": "",
                "residenceSize": 366020,
                "residenceSizeDesc": "",
                "commerceSize": 93115,
                "commerceSizeDesc": "",
                "officeSize": 0,
                "officeSizeDesc": "",
                "otherSize": 0,
                "otherSizeDesc": "",
                "parkSize": 116460,
                "parkSizeDesc": "",
                "otherSize1": 0,
                "otherSize1Desc": "",
                "winner": "佛山市新锋房地产开发有限公司",
                "winnerDesc": "",
                "price": 128601.77,
                "priceDesc": "",
                "date": "2009-12-30",
                "dateDesc": "",
                "contract": "440601-2010-100180",
                "contractDesc": "",
                "license": "佛禅国用(2012)第1003072号|佛禅国用(2012)第1008625号|佛禅国用(2012)第1008624号",
                "licenseDesc": ""
            }
        },
        {
            "license": {
                "id": "70C906826C7C",
                "datetime": "2016-06-17 19:50:09",
                "planId": "FC3EDE99C78D",
                "number": "建字第440604201600093号",
                "numberDesc": "",
                "name": "",
                "nameDesc": "",
                "date": "2016-04-22",
                "dateDesc": "",
                "residenceSize": 43509.24,
                "residenceSizeDesc": "",
                "commerceSize": 1512.88,
                "commerceSizeDesc": "",
                "officeSize": 0,
                "officeSizeDesc": "",
                "otherSize": 294.2,
                "otherSizeDesc": "",
                "parkSize": 6379.95,
                "parkSizeDesc": "",
                "otherSize1": 2374.79,
                "otherSize1Desc": ""
            },
            "plan": {
                "id": "FC3EDE99C78D",
                "datetime": "2016-06-18 16:21:57",
                "landId": "FFFBB3D58A0B",
                "project": "泷景花园",
                "projectDesc": "",
                "use": "居住用地，兼容商业办公、文化娱乐用地等",
                "useDesc": "",
                "developer": "佛山市新锋房地产开发有限公司",
                "developerDesc": ""
            },
            "land": {
                "id": "FFFBB3D58A0B",
                "datetime": "2016-06-17 15:28:43",
                "number": "佛禅(挂)2009-014",
                "numberDesc": "",
                "town": "石湾",
                "townDesc": "",
                "location": "佛山大道东侧、前进路南侧、东平河北侧、纵二路西侧",
                "locationDesc": "",
                "size": 155956.28,
                "sizeDesc": "",
                "use": "居住用地，兼容商业办公、文化娱乐",
                "useDesc": "",
                "diy": false,
                "diyDesc": "",
                "residenceSize": 366020,
                "residenceSizeDesc": "",
                "commerceSize": 93115,
                "commerceSizeDesc": "",
                "officeSize": 0,
                "officeSizeDesc": "",
                "otherSize": 0,
                "otherSizeDesc": "",
                "parkSize": 116460,
                "parkSizeDesc": "",
                "otherSize1": 0,
                "otherSize1Desc": "",
                "winner": "佛山市新锋房地产开发有限公司",
                "winnerDesc": "",
                "price": 128601.77,
                "priceDesc": "",
                "date": "2009-12-30",
                "dateDesc": "",
                "contract": "440601-2010-100180",
                "contractDesc": "",
                "license": "佛禅国用(2012)第1003072号|佛禅国用(2012)第1008625号|佛禅国用(2012)第1008624号",
                "licenseDesc": ""
            }
        },
        {
            "license": {
                "id": "3D456F697587",
                "datetime": "2016-06-17 19:52:46",
                "planId": "FC3EDE99C78D",
                "number": "建字第440604201600097号",
                "numberDesc": "",
                "name": "",
                "nameDesc": "",
                "date": "2016-04-22",
                "dateDesc": "",
                "residenceSize": 29294.98,
                "residenceSizeDesc": "",
                "commerceSize": 1190.05,
                "commerceSizeDesc": "",
                "officeSize": 0,
                "officeSizeDesc": "",
                "otherSize": 0,
                "otherSizeDesc": "",
                "parkSize": 3001.79,
                "parkSizeDesc": "",
                "otherSize1": 1958.46,
                "otherSize1Desc": ""
            },
            "plan": {
                "id": "FC3EDE99C78D",
                "datetime": "2016-06-18 16:21:57",
                "landId": "FFFBB3D58A0B",
                "project": "泷景花园",
                "projectDesc": "",
                "use": "居住用地，兼容商业办公、文化娱乐用地等",
                "useDesc": "",
                "developer": "佛山市新锋房地产开发有限公司",
                "developerDesc": ""
            },
            "land": {
                "id": "FFFBB3D58A0B",
                "datetime": "2016-06-17 15:28:43",
                "number": "佛禅(挂)2009-014",
                "numberDesc": "",
                "town": "石湾",
                "townDesc": "",
                "location": "佛山大道东侧、前进路南侧、东平河北侧、纵二路西侧",
                "locationDesc": "",
                "size": 155956.28,
                "sizeDesc": "",
                "use": "居住用地，兼容商业办公、文化娱乐",
                "useDesc": "",
                "diy": false,
                "diyDesc": "",
                "residenceSize": 366020,
                "residenceSizeDesc": "",
                "commerceSize": 93115,
                "commerceSizeDesc": "",
                "officeSize": 0,
                "officeSizeDesc": "",
                "otherSize": 0,
                "otherSizeDesc": "",
                "parkSize": 116460,
                "parkSizeDesc": "",
                "otherSize1": 0,
                "otherSize1Desc": "",
                "winner": "佛山市新锋房地产开发有限公司",
                "winnerDesc": "",
                "price": 128601.77,
                "priceDesc": "",
                "date": "2009-12-30",
                "dateDesc": "",
                "contract": "440601-2010-100180",
                "contractDesc": "",
                "license": "佛禅国用(2012)第1003072号|佛禅国用(2012)第1008625号|佛禅国用(2012)第1008624号",
                "licenseDesc": ""
            }
        },
        {
            "license": {
                "id": "BA0F1E4412C6",
                "datetime": "2016-06-17 20:00:49",
                "planId": "FC3EDE99C78D",
                "number": "建字第440604201600098号",
                "numberDesc": "",
                "name": "",
                "nameDesc": "",
                "date": "2016-04-22",
                "dateDesc": "",
                "residenceSize": 30931.56,
                "residenceSizeDesc": "",
                "commerceSize": 1154.64,
                "commerceSizeDesc": "",
                "officeSize": 0,
                "officeSizeDesc": "",
                "otherSize": 0,
                "otherSizeDesc": "",
                "parkSize": 4217.77,
                "parkSizeDesc": "",
                "otherSize1": 1606.2,
                "otherSize1Desc": ""
            },
            "plan": {
                "id": "FC3EDE99C78D",
                "datetime": "2016-06-18 16:21:57",
                "landId": "FFFBB3D58A0B",
                "project": "泷景花园",
                "projectDesc": "",
                "use": "居住用地，兼容商业办公、文化娱乐用地等",
                "useDesc": "",
                "developer": "佛山市新锋房地产开发有限公司",
                "developerDesc": ""
            },
            "land": {
                "id": "FFFBB3D58A0B",
                "datetime": "2016-06-17 15:28:43",
                "number": "佛禅(挂)2009-014",
                "numberDesc": "",
                "town": "石湾",
                "townDesc": "",
                "location": "佛山大道东侧、前进路南侧、东平河北侧、纵二路西侧",
                "locationDesc": "",
                "size": 155956.28,
                "sizeDesc": "",
                "use": "居住用地，兼容商业办公、文化娱乐",
                "useDesc": "",
                "diy": false,
                "diyDesc": "",
                "residenceSize": 366020,
                "residenceSizeDesc": "",
                "commerceSize": 93115,
                "commerceSizeDesc": "",
                "officeSize": 0,
                "officeSizeDesc": "",
                "otherSize": 0,
                "otherSizeDesc": "",
                "parkSize": 116460,
                "parkSizeDesc": "",
                "otherSize1": 0,
                "otherSize1Desc": "",
                "winner": "佛山市新锋房地产开发有限公司",
                "winnerDesc": "",
                "price": 128601.77,
                "priceDesc": "",
                "date": "2009-12-30",
                "dateDesc": "",
                "contract": "440601-2010-100180",
                "contractDesc": "",
                "license": "佛禅国用(2012)第1003072号|佛禅国用(2012)第1008625号|佛禅国用(2012)第1008624号",
                "licenseDesc": ""
            }
        },
        {
            "license": {
                "id": "752B25577C91",
                "datetime": "2016-06-17 19:59:26",
                "planId": "FC3EDE99C78D",
                "number": "建字第440604201600099号",
                "numberDesc": "",
                "name": "",
                "nameDesc": "",
                "date": "2016-04-22",
                "dateDesc": "",
                "residenceSize": 23558.97,
                "residenceSizeDesc": "",
                "commerceSize": 773.58,
                "commerceSizeDesc": "",
                "officeSize": 0,
                "officeSizeDesc": "",
                "otherSize": 578.75,
                "otherSizeDesc": "",
                "parkSize": 3016.65,
                "parkSizeDesc": "",
                "otherSize1": 1279.33,
                "otherSize1Desc": ""
            },
            "plan": {
                "id": "FC3EDE99C78D",
                "datetime": "2016-06-18 16:21:57",
                "landId": "FFFBB3D58A0B",
                "project": "泷景花园",
                "projectDesc": "",
                "use": "居住用地，兼容商业办公、文化娱乐用地等",
                "useDesc": "",
                "developer": "佛山市新锋房地产开发有限公司",
                "developerDesc": ""
            },
            "land": {
                "id": "FFFBB3D58A0B",
                "datetime": "2016-06-17 15:28:43",
                "number": "佛禅(挂)2009-014",
                "numberDesc": "",
                "town": "石湾",
                "townDesc": "",
                "location": "佛山大道东侧、前进路南侧、东平河北侧、纵二路西侧",
                "locationDesc": "",
                "size": 155956.28,
                "sizeDesc": "",
                "use": "居住用地，兼容商业办公、文化娱乐",
                "useDesc": "",
                "diy": false,
                "diyDesc": "",
                "residenceSize": 366020,
                "residenceSizeDesc": "",
                "commerceSize": 93115,
                "commerceSizeDesc": "",
                "officeSize": 0,
                "officeSizeDesc": "",
                "otherSize": 0,
                "otherSizeDesc": "",
                "parkSize": 116460,
                "parkSizeDesc": "",
                "otherSize1": 0,
                "otherSize1Desc": "",
                "winner": "佛山市新锋房地产开发有限公司",
                "winnerDesc": "",
                "price": 128601.77,
                "priceDesc": "",
                "date": "2009-12-30",
                "dateDesc": "",
                "contract": "440601-2010-100180",
                "contractDesc": "",
                "license": "佛禅国用(2012)第1003072号|佛禅国用(2012)第1008625号|佛禅国用(2012)第1008624号",
                "licenseDesc": ""
            }
        },
        {
            "license": {
                "id": "AE3CF6A76546",
                "datetime": "2016-06-17 20:05:39",
                "planId": "FC3EDE99C78D",
                "number": "建字第440604201600096号",
                "numberDesc": "",
                "name": "",
                "nameDesc": "",
                "date": "2016-04-22",
                "dateDesc": "",
                "residenceSize": 45290.9,
                "residenceSizeDesc": "",
                "commerceSize": 1708.3,
                "commerceSizeDesc": "",
                "officeSize": 0,
                "officeSizeDesc": "",
                "otherSize": 0,
                "otherSizeDesc": "",
                "parkSize": 7587.38,
                "parkSizeDesc": "",
                "otherSize1": 2161.4,
                "otherSize1Desc": ""
            },
            "plan": {
                "id": "FC3EDE99C78D",
                "datetime": "2016-06-18 16:21:57",
                "landId": "FFFBB3D58A0B",
                "project": "泷景花园",
                "projectDesc": "",
                "use": "居住用地，兼容商业办公、文化娱乐用地等",
                "useDesc": "",
                "developer": "佛山市新锋房地产开发有限公司",
                "developerDesc": ""
            },
            "land": {
                "id": "FFFBB3D58A0B",
                "datetime": "2016-06-17 15:28:43",
                "number": "佛禅(挂)2009-014",
                "numberDesc": "",
                "town": "石湾",
                "townDesc": "",
                "location": "佛山大道东侧、前进路南侧、东平河北侧、纵二路西侧",
                "locationDesc": "",
                "size": 155956.28,
                "sizeDesc": "",
                "use": "居住用地，兼容商业办公、文化娱乐",
                "useDesc": "",
                "diy": false,
                "diyDesc": "",
                "residenceSize": 366020,
                "residenceSizeDesc": "",
                "commerceSize": 93115,
                "commerceSizeDesc": "",
                "officeSize": 0,
                "officeSizeDesc": "",
                "otherSize": 0,
                "otherSizeDesc": "",
                "parkSize": 116460,
                "parkSizeDesc": "",
                "otherSize1": 0,
                "otherSize1Desc": "",
                "winner": "佛山市新锋房地产开发有限公司",
                "winnerDesc": "",
                "price": 128601.77,
                "priceDesc": "",
                "date": "2009-12-30",
                "dateDesc": "",
                "contract": "440601-2010-100180",
                "contractDesc": "",
                "license": "佛禅国用(2012)第1003072号|佛禅国用(2012)第1008625号|佛禅国用(2012)第1008624号",
                "licenseDesc": ""
            }
        },
        {
            "license": {
                "id": "3918823FB192",
                "datetime": "2016-06-17 20:10:03",
                "planId": "FC3EDE99C78D",
                "number": "建字第440604201600094号",
                "numberDesc": "",
                "name": "",
                "nameDesc": "",
                "date": "2016-04-22",
                "dateDesc": "",
                "residenceSize": 54876.99,
                "residenceSizeDesc": "",
                "commerceSize": 2148.88,
                "commerceSizeDesc": "",
                "officeSize": 0,
                "officeSizeDesc": "",
                "otherSize": 0,
                "otherSizeDesc": "",
                "parkSize": 10711.7,
                "parkSizeDesc": "",
                "otherSize1": 2556.3,
                "otherSize1Desc": ""
            },
            "plan": {
                "id": "FC3EDE99C78D",
                "datetime": "2016-06-18 16:21:57",
                "landId": "FFFBB3D58A0B",
                "project": "泷景花园",
                "projectDesc": "",
                "use": "居住用地，兼容商业办公、文化娱乐用地等",
                "useDesc": "",
                "developer": "佛山市新锋房地产开发有限公司",
                "developerDesc": ""
            },
            "land": {
                "id": "FFFBB3D58A0B",
                "datetime": "2016-06-17 15:28:43",
                "number": "佛禅(挂)2009-014",
                "numberDesc": "",
                "town": "石湾",
                "townDesc": "",
                "location": "佛山大道东侧、前进路南侧、东平河北侧、纵二路西侧",
                "locationDesc": "",
                "size": 155956.28,
                "sizeDesc": "",
                "use": "居住用地，兼容商业办公、文化娱乐",
                "useDesc": "",
                "diy": false,
                "diyDesc": "",
                "residenceSize": 366020,
                "residenceSizeDesc": "",
                "commerceSize": 93115,
                "commerceSizeDesc": "",
                "officeSize": 0,
                "officeSizeDesc": "",
                "otherSize": 0,
                "otherSizeDesc": "",
                "parkSize": 116460,
                "parkSizeDesc": "",
                "otherSize1": 0,
                "otherSize1Desc": "",
                "winner": "佛山市新锋房地产开发有限公司",
                "winnerDesc": "",
                "price": 128601.77,
                "priceDesc": "",
                "date": "2009-12-30",
                "dateDesc": "",
                "contract": "440601-2010-100180",
                "contractDesc": "",
                "license": "佛禅国用(2012)第1003072号|佛禅国用(2012)第1008625号|佛禅国用(2012)第1008624号",
                "licenseDesc": ""
            }
        }
    ],
    "total": 66
}